Ser_in_par_out/sipo.v
module sipos (
    input clk,input si,output reg [3:0]q
);
    always @(posedge clk) begin
        //right shift
        q[3]<=si;
        q[2]<=q[3];
        q[1]<=q[2];
        q[0]<=q[1];
    end
endmodule

Ser_in_par_out/sipo_tb.v
module testbench;
reg clk;
reg si;

wire [3:0]q;
sipos uut(.clk(clk),.si(si),.q(q));

    initial
    begin
        $dumpfile("sipoo.vcd");
        $dumpvars(1);
        clk = 0;
        si = 1;
        #10
        si = 0;
        #10
        si = 0;
        #10
        si = 1;
        #10
    $monitor($time, "Clk:%b , Si: %b , Q: %b ",clk,si,q);
    end
    $finish;
    always #15 clk = ~clk;
endmodule

Ser_in_par_out/sipoo.vcd
$date
	Tue Jun  6 10:16:29 2023
$end
$version
	Icarus Verilog
$end
$timescale
	1s
$end
$scope module testbench $end
$var wire 4 ! q [3:0] $end
$var reg 1 " clk $end
$var reg 1 # si $end
$upscope $end
$enddefinitions $end
#0
$dumpvars
1#
0"
bx !
$end
#10
b1xxx !
1"
#20
0"
#30
b11xx !
1"
#40
0"
#50
b111x !
1"
#60
0"
#70
b1111 !
1"
#80
0"
#90
1"
#100
0"
0#
#110
b111 !
1"
#120
0"
#130
b11 !
1"
#140
0"
#150
b1 !
1"
#160
0"
#170
b0 !
1"
#180
0"
#190
1"
#200
0"
#210
1"
#220
0"
#230
1"
#240
0"
#250
1"
#260
0"
#270
1"
#280
0"
#290
1"
#300
0"
1#
#310
b1000 !
1"
#320
0"
#330
b1100 !
1"
#340
0"
#350
b1110 !
1"
#360
0"
#370
b1111 !
1"
