Full_sub/full_sub.v
// Full Subtractor module
module full_subtractor(A, B, Cin, Diff, Borrow);
  input A, B, Cin;
  output Diff, Borrow;
  
  assign Diff = A ^ B ^ Cin;
  assign Borrow = (~A & B) | (~A & Cin) | (B & Cin);
endmodule

Full_sub/fs_tb.v
// Full Subtractor Testbench
module full_subtractor_tb;
  reg A, B, Cin;
  wire Diff, Borrow;
  
  full_subtractor uut(A, B, Cin, Diff, Borrow);
  
  initial begin
  $dumpfile("full_subtractor.vcd");
    $dumpvars(0, full_subtractor_tb);
    // Test case 1
    A = 0;
    B = 0;
    Cin = 0;
    #10;
    
    // Test case 2
    A = 1;
    B = 0;
    Cin = 0;
    #10;
    
    // Test case 3
    A = 0;
    B = 1;
    Cin = 0;
    #10;
    
    // Test case 4
    A = 1;
    B = 1;
    Cin = 0;
    #10;
    
    // Test case 5
    A = 0;
    B = 0;
    Cin = 1;
    #10;
    
    // Test case 6
    A = 1;
    B = 0;
    Cin = 1;
    #10;
    
    // Test case 7
    A = 0;
    B = 1;
    Cin = 1;
    #10;
    
    // Test case 8
    A = 1;
    B = 1;
    Cin = 1;
    #10;
    
    $finish;
  end
endmodule

Full_sub/full_subtractor.vcd
$date
	Fri Jun  2 10:44:07 2023
$end
$version
	Icarus Verilog
$end
$timescale
	1s
$end
$scope module full_subtractor_tb $end
$var wire 1 ! Diff $end
$var wire 1 " Borrow $end
$var reg 1 # A $end
$var reg 1 $ B $end
$var reg 1 % Cin $end
$scope module uut $end
$var wire 1 # A $end
$var wire 1 $ B $end
$var wire 1 " Borrow $end
$var wire 1 % Cin $end
$var wire 1 ! Diff $end
$upscope $end
$upscope $end
$enddefinitions $end
#0
$dumpvars
0%
0$
0#
0"
0!
$end
#10
1!
1#
#20
1"
1$
0#
#30
0"
0!
1#
#40
1"
1!
1%
0$
0#
#50
0"
0!
1#
#60
1"
1$
0#
#70
1!
1#
