Ser_in_ser_out_s/sisos.v
module siso_shift_register (
  input wire clk,
  input wire reset,
  input wire serial_in,
  output wire serial_out
);

  reg [3:0] shift_reg;

  always @(posedge clk or posedge reset) begin
    if (reset)
      shift_reg <= 4'b0000;
    else
      shift_reg <= {shift_reg[2:0], serial_in};
  end

  assign serial_out = shift_reg[3];

endmodule

Ser_in_ser_out_s/siso_tb.v
module siso_shift_register_tb;

  reg clk;
  reg reset;
  reg serial_in;
  wire serial_out;

  siso_shift_register dut (
    .clk(clk),
    .reset(reset),
    .serial_in(serial_in),
    .serial_out(serial_out)
  );

  initial begin
    clk = 0;
    reset = 1;
    serial_in = 0;

    #10 reset = 0;

    // Testcase 1: Shift in 1010
    serial_in = 1;
    #10;
    serial_in = 0;
    #10;
    serial_in = 1;
    #10;
    serial_in = 0;
    #10;

    // Testcase 2: Shift in 0011
    serial_in = 0;
    #10;
    serial_in = 0;
    #10;
    serial_in = 1;
    #10;
    serial_in = 1;
    #10;

    $finish;
  end

  always begin
    #5 clk = ~clk;
  end

  initial begin
    $dumpfile("siso_shift_register_tb.vcd");
    $dumpvars(0, siso_shift_register_tb);
    $monitor("Time=%0t: clk=%b, reset=%b, serial_in=%b, serial_out=%b",
      $time, clk, reset, serial_in, serial_out);
  end

endmodule

Ser_in_ser_out_s/siso_shift_register_tb.vcd
$date
	Mon Jun  5 14:54:07 2023
$end
$version
	Icarus Verilog
$end
$timescale
	1s
$end
$scope module siso_shift_register_tb $end
$var wire 1 ! serial_out $end
$var reg 1 " clk $end
$var reg 1 # reset $end
$var reg 1 $ serial_in $end
$scope module dut $end
$var wire 1 " clk $end
$var wire 1 # reset $end
$var wire 1 $ serial_in $end
$var wire 1 ! serial_out $end
$var reg 4 % shift_reg [3:0] $end
$upscope $end
$upscope $end
$enddefinitions $end
#0
$dumpvars
b0 %
0$
1#
0"
0!
$end
#5
1"
#10
0"
1$
0#
#15
b1 %
1"
#20
0"
0$
#25
b10 %
1"
#30
0"
1$
#35
b101 %
1"
#40
0"
0$
#45
1!
b1010 %
1"
#50
0"
#55
0!
b100 %
1"
#60
0"
#65
1!
b1000 %
1"
#70
0"
1$
#75
0!
b1 %
1"
#80
0"
#85
b11 %
1"
