logic_circuits/lc2.v
module lc2(a,b,c,d,w,x,y,z,q);
input a,b,c,d;
output w,x,y,z,q;

and(w,a,b);
not(x,c);
or(y,w,x);
and(z,y,d);
not(q,z);

endmodule

logic_circuits/lc2_tb.v
module lc2_tb;
reg a,b,c,d;
wire w,x,y,z,q;

lc2 uut(.a(a),.b(b),.c(c),.d(d),.w(w),.x(x),.y(y),.z(z),.q(q));
initial begin
    $dumpfile("lc2.vcd");
    $dumpvars(0,lc2_tb);
    a = 0; b = 0; c=0; d=0;
    #10
    $display("a | b | c | d | w | x | y | z | Output" );
    $display("%b | %b | %b | %b | %b | %b | %b | %b | %b" , a,b,c,d,w,x,y,z,q);
    a = 0; b = 0; c=0; d=1;
    #10
    $display("%b | %b | %b | %b | %b | %b | %b | %b | %b" , a,b,c,d,w,x,y,z,q);
    a = 0; b = 0; c=1; d=0;
    #10
    $display("%b | %b | %b | %b | %b | %b | %b | %b | %b" , a,b,c,d,w,x,y,z,q);
    a = 0; b = 0; c=1; d=1;
    #10
    $display("%b | %b | %b | %b | %b | %b | %b | %b | %b" , a,b,c,d,w,x,y,z,q);
    a = 0; b = 1; c=0; d=0;
    #10
    $display("%b | %b | %b | %b | %b | %b | %b | %b | %b" , a,b,c,d,w,x,y,z,q);
    a = 0; b = 1; c=0; d=1;
    #10
    $display("%b | %b | %b | %b | %b | %b | %b | %b | %b" , a,b,c,d,w,x,y,z,q);
    a = 0; b = 1; c=1; d=0;
    #10
    $display("%b | %b | %b | %b | %b | %b | %b | %b | %b" , a,b,c,d,w,x,y,z,q);
    a = 0; b = 1; c=1; d=1;
    #10
    $display("%b | %b | %b | %b | %b | %b | %b | %b | %b" , a,b,c,d,w,x,y,z,q);
    end
endmodule

logic_circuits/lc2.vcd
$date
	Tue Jan 30 09:15:10 2024
$end
$version
	Icarus Verilog
$end
$timescale
	1s
$end
$scope module lc2_tb $end
$var wire 1 ! z $end
$var wire 1 " y $end
$var wire 1 # x $end
$var wire 1 $ w $end
$var wire 1 % q $end
$var reg 1 & a $end
$var reg 1 ' b $end
$var reg 1 ( c $end
$var reg 1 ) d $end
$scope module uut $end
$var wire 1 & a $end
$var wire 1 ' b $end
$var wire 1 ( c $end
$var wire 1 ) d $end
$var wire 1 % q $end
$var wire 1 $ w $end
$var wire 1 # x $end
$var wire 1 " y $end
$var wire 1 ! z $end
$upscope $end
$upscope $end
$enddefinitions $end
#0
$dumpvars
0)
0(
0'
0&
1%
0$
1#
1"
0!
$end
#10
0%
1!
1)
#20
1%
0"
0!
0#
0)
1(
#30
1)
#40
1"
1#
0)
0(
1'
#50
0%
1!
1)
#60
1%
0"
0!
0#
0)
1(
#70
1)
