logic_circuits/lc3.v
module lc3(a,b,c,w,x,y,z,q);
input a,b,c ;
output w,x,y,z,q;

and(w,a,b);
or(x,b,c);
and(y,c,b);
and(z,x,y);
or(q,w,z);

endmodule

logic_circuits/lc3_tb.v
module lc3_tb;
reg a,b,c;
wire w,x,y,z,q;

lc3 uut(.a(a),.b(b),.c(c),.w(w),.x(x),.y(y),.z(z),.q(q));

initial begin
    $dumpfile("lc3.vcd");
    $dumpvars(0,lc3_tb);
    a = 0; b = 0; c=0;
    #10
    $display("a | b | c | w | x | y | z | Output" );
    $display("%b | %b | %b | %b | %b | %b | %b | %b" , a,b,c,w,x,y,z,q);
    a = 0; b = 0; c=1;
    #10
    $display("%b | %b | %b | %b | %b | %b | %b | %b" , a,b,c,w,x,y,z,q);
    a = 0; b = 1; c=0;
    #10
    $display("%b | %b | %b | %b | %b | %b | %b | %b" , a,b,c,w,x,y,z,q);
    a = 0; b = 1; c=1;
    #10
    $display("%b | %b | %b | %b | %b | %b | %b | %b" , a,b,c,w,x,y,z,q);
    a = 1; b = 0; c=0;
    #10
    $display("%b | %b | %b | %b | %b | %b | %b | %b" , a,b,c,w,x,y,z,q);
    a = 1; b = 0; c=1;
    #10
    $display("%b | %b | %b | %b | %b | %b | %b | %b" , a,b,c,w,x,y,z,q);
    a = 1; b = 1; c=0;
    #10
    $display("%b | %b | %b | %b | %b | %b | %b | %b" , a,b,c,w,x,y,z,q);
    a = 1; b = 1; c=1;
    #10
    $display("%b | %b | %b | %b | %b | %b | %b | %b" , a,b,c,w,x,y,z,q);
    end
endmodule

logic_circuits/lc3.vcd
$date
	Tue Jan 30 09:16:39 2024
$end
$version
	Icarus Verilog
$end
$timescale
	1s
$end
$scope module lc3_tb $end
$var wire 1 ! z $end
$var wire 1 " y $end
$var wire 1 # x $end
$var wire 1 $ w $end
$var wire 1 % q $end
$var reg 1 & a $end
$var reg 1 ' b $end
$var reg 1 ( c $end
$scope module uut $end
$var wire 1 & a $end
$var wire 1 ' b $end
$var wire 1 ( c $end
$var wire 1 % q $end
$var wire 1 $ w $end
$var wire 1 # x $end
$var wire 1 " y $end
$var wire 1 ! z $end
$upscope $end
$upscope $end
$enddefinitions $end
#0
$dumpvars
0(
0'
0&
0%
0$
0#
0"
0!
$end
#10
1#
1(
#20
0(
1'
#30
1%
1!
1"
1(
#40
0%
0!
0#
0"
0(
0'
1&
#50
1#
1(
#60
1%
1$
0(
1'
#70
1!
1"
1(
