Flip_Flops/SR_ff/sr.v
module sr_flip_flop(
    input s,       
    input r,       
    input clk,     
    output reg q,  
    output reg q_bar 
);

    always @(posedge clk)
    begin
        if (r)
        begin
            q <= 1'b0;     
            q_bar <= 1'b1; 
        end
        else if (s)
        begin
            q <= 1'b1;     
            q_bar <= 1'b0; 
        end
    end

endmodule

Flip_Flops/SR_ff/tb_sr.v
module tb_sr_flip_flop;
    reg s, r, clk;
    wire q, q_bar;
    sr_flip_flop sr_ff_inst(
        .s(s),
        .r(r),
        .clk(clk),
        .q(q),
        .q_bar(q_bar)
    );

    initial begin
        $dumpfile("waveform.vcd");
        $dumpvars(0, tb_sr_flip_flop);
        clk = 1'b0;       
        #5 s = 1'b1;      
        #5 r = 1'b0;      
        #5 s = 1'b0;      
        #5 r = 1'b1;      
        #5 s = 1'b1;      
        #5 r = 1'b0;      
        #5 s = 1'b0;      
        #5 r = 1'b1;      
        #5 $finish;
    end
    always #5 clk = ~clk;

    initial begin
        $monitor("Time=%0t, s=%b, r=%b, clk=%b, q=%b, q_bar=%b", $time, s, r, clk, q, q_bar);
    end
endmodule

Flip_Flops/SR_ff/waveform.vcd
$date
	Fri Apr 12 07:54:39 2024
$end
$version
	Icarus Verilog
$end
$timescale
	1s
$end
$scope module tb_sr_flip_flop $end
$var wire 1 ! q_bar $end
$var wire 1 " q $end
$var reg 1 # clk $end
$var reg 1 $ r $end
$var reg 1 % s $end
$scope module sr_ff_inst $end
$var wire 1 # clk $end
$var wire 1 $ r $end
$var wire 1 % s $end
$var reg 1 " q $end
$var reg 1 ! q_bar $end
$upscope $end
$upscope $end
$enddefinitions $end
#0
$dumpvars
x%
x$
0#
x"
x!
$end
#5
0!
1"
1#
1%
#10
0#
0$
#15
1#
0%
#20
0#
1$
#25
1!
0"
1#
1%
#30
0#
0$
#35
1#
0%
#40
0#
1$
