Code Converters/dectobin/dectobin.v
module dectobin (
    input [3:0] decimal,
    output reg [3:0] binary
);

always @(*) begin
    case(decimal)
        0: binary = 4'b0000;
        1: binary = 4'b0001;
        2: binary = 4'b0010;
        3: binary = 4'b0011;
        4: binary = 4'b0100;
        5: binary = 4'b0101;
        6: binary = 4'b0110;
        7: binary = 4'b0111;
        8: binary = 4'b1000;
        9: binary = 4'b1001;
        default: binary = 4'bxxxx; 
    endcase
end

endmodule

Code Converters/dectobin/tb_dectobin.v
module tb_dectobin;
reg [3:0] decimal;
wire [3:0] binary;

dectobin uut (.decimal(decimal), .binary(binary));

initial begin
    $dumpfile("dectobin.vcd");
    $dumpvars(0, tb_dectobin);
    $monitor($time," Input: %d, Output: %b", decimal, binary);
    decimal = 4'b0000;
    #10 decimal = 4'b0001;
    #10 decimal = 4'b0010;
    #10 decimal = 4'b0011;
    #10 decimal = 4'b0100;
    #10 decimal = 4'b0101;
    #10 decimal = 4'b0110;
    #10 decimal = 4'b0111;
    #10 decimal = 4'b1000;
    #10 decimal = 4'b1001;
    #10 $finish;
end
endmodule

Code Converters/dectobin/dectobin.vcd
$date
	Mon Mar  4 15:56:12 2024
$end
$version
	Icarus Verilog
$end
$timescale
	1s
$end
$scope module tb_dectobin $end
$var wire 4 ! binary [3:0] $end
$var reg 4 " decimal [3:0] $end
$scope module uut $end
$var wire 4 # decimal [3:0] $end
$var reg 4 $ binary [3:0] $end
$upscope $end
$upscope $end
$enddefinitions $end
#0
$dumpvars
b0 $
b0 #
b0 "
b0 !
$end
#10
b1 !
b1 $
b1 "
b1 #
#20
b10 !
b10 $
b10 "
b10 #
#30
b11 !
b11 $
b11 "
b11 #
#40
b100 !
b100 $
b100 "
b100 #
#50
b101 !
b101 $
b101 "
b101 #
#60
b110 !
b110 $
b110 "
b110 #
#70
b111 !
b111 $
b111 "
b111 #
#80
b1000 !
b1000 $
b1000 "
b1000 #
#90
b1001 !
b1001 $
b1001 "
b1001 #
