JK_flip_flop/jk.v
module jk_flip_flop (
  input wire clk,
  input wire j,
  input wire k,
  input wire reset,
  output reg q,
  output reg q_bar
);

  always @(posedge clk or posedge reset) begin
    if (reset)
      q <= 1'b0;
    else if (j && ~k)
      q <= 1'b1;
    else if (~j && k)
      q <= 1'b0;
    else if (j && k)
      q <= ~q;
  end

  always @(q) begin
    q_bar <= ~q;
  end

endmodule

JK_flip_flop/jk_tb.v
module testbench;

  reg clk, reset, j, k;
  wire q, q_bar;

  jk_flip_flop dut (
    .clk(clk),
    .j(j),
    .k(k),
    .reset(reset),
    .q(q),
    .q_bar(q_bar)
  );

  initial begin
    $dumpfile("jk.vcd");
    $dumpvars(1);
    clk = 0;
    reset = 1;
    j = 0;
    k = 0;

    #5 reset = 0;

    #5 j = 1;
    #10 j = 0;

    #5 k = 1;
    #10 k = 0;

    #5 j = 1;
    #5 k = 1;
    #10 j = 0;
    #10 k = 0;

    #5 j = 0;
    #5 k = 0;

    #5 j = 1;
    #5 k = 1;

    #5 $finish;
  end

  always #1 clk = ~clk;

endmodule

JK_flip_flop/jk.vcd
$date
	Wed Apr 10 13:17:39 2024
$end
$version
	Icarus Verilog
$end
$timescale
	1s
$end
$scope module testbench $end
$var wire 1 ! q_bar $end
$var wire 1 " q $end
$var reg 1 # clk $end
$var reg 1 $ j $end
$var reg 1 % k $end
$var reg 1 & reset $end
$upscope $end
$enddefinitions $end
#0
$dumpvars
1&
0%
0$
0#
0"
1!
$end
#1
1#
#2
0#
#3
1#
#4
0#
#5
1#
0&
#6
0#
#7
1#
#8
0#
#9
1#
#10
0#
1$
#11
0!
1"
1#
#12
0#
#13
1#
#14
0#
#15
1#
#16
0#
#17
1#
#18
0#
#19
1#
#20
0#
0$
#21
1#
#22
0#
#23
1#
#24
0#
#25
1!
0"
1#
1%
#26
0#
#27
1#
#28
0#
#29
1#
#30
0#
#31
1#
#32
0#
#33
1#
#34
0#
#35
1#
0%
#36
0#
#37
1#
#38
0#
#39
1#
#40
0#
1$
#41
0!
1"
1#
#42
0#
#43
1#
#44
0#
#45
1!
0"
1#
1%
#46
0#
#47
0!
1"
1#
#48
0#
#49
1!
0"
1#
#50
0#
#51
0!
1"
1#
#52
0#
#53
1!
0"
1#
#54
0#
#55
1#
0$
#56
0#
#57
1#
#58
0#
#59
1#
#60
0#
#61
1#
#62
0#
#63
1#
#64
0#
#65
1#
0%
#66
0#
#67
1#
#68
0#
#69
1#
#70
0#
#71
1#
#72
0#
#73
1#
#74
0#
#75
1#
#76
0#
#77
1#
#78
0#
#79
1#
#80
0#
1$
#81
0!
1"
1#
#82
0#
#83
1#
#84
0#
#85
1!
0"
1#
1%
#86
0#
#87
0!
1"
1#
#88
0#
#89
1!
0"
1#
