Adders and Subtractors/Full_adder/full_adder.v
module full_adder(a, b, cin,sum, cout);
	input a,b,cin;
	output sum,cout;
   	assign sum = a ^ b ^ cin;
   	assign cout = (a & b) | (cin & (a ^ b));
endmodule

Adders and Subtractors/Full_adder/fa_tb.v
module fa_tb;
    reg a, b, cin;
    wire sum, cout;

    full_adder DUT(a, b, cin, sum, cout);

    initial begin
    	$dumpfile("full_adder.vcd"); 
        $dumpvars(0, fa_tb); 
        $display("Full Adder Testbench");
        $display("--------------------");
        $display("Inputs\t\t|\tOutputs");
        $display("--------------------");
        a = 0; b = 0; cin = 0;
        #10;
        $display("%b %b %b\t|\t%b %b", a, b, cin, sum, cout);
        a = 0; b = 1; cin = 0;
        #10;
        $display("%b %b %b\t|\t%b %b", a, b, cin, sum, cout);
        a = 1; b = 0; cin = 0;
        #10;
        $display("%b %b %b\t|\t%b %b", a, b, cin, sum, cout);
        a = 1; b = 1; cin = 0;
        #10;
        $display("%b %b %b\t|\t%b %b", a, b, cin, sum, cout);
        a = 0; b = 0; cin = 1;
        #10;
        $display("%b %b %b\t|\t%b %b", a, b, cin, sum, cout);
        a = 0; b = 1; cin = 1;
        #10;
        $display("%b %b %b\t|\t%b %b", a, b, cin, sum, cout);
        a = 1; b = 0; cin = 1;
        #10;
        $display("%b %b %b\t|\t%b %b", a, b, cin, sum, cout);
        a = 1; b = 1; cin = 1;
        #10;
        $display("%b %b %b\t|\t%b %b", a, b, cin, sum, cout);
        $finish;
    end
endmodule

Adders and Subtractors/Full_adder/full_adder.vcd
$date
	Wed Jan 31 09:32:45 2024
$end
$version
	Icarus Verilog
$end
$timescale
	1s
$end
$scope module fa_tb $end
$var wire 1 ! sum $end
$var wire 1 " cout $end
$var reg 1 # a $end
$var reg 1 $ b $end
$var reg 1 % cin $end
$scope module DUT $end
$var wire 1 # a $end
$var wire 1 $ b $end
$var wire 1 % cin $end
$var wire 1 " cout $end
$var wire 1 ! sum $end
$upscope $end
$upscope $end
$enddefinitions $end
#0
$dumpvars
0%
0$
0#
0"
0!
$end
#10
1!
1$
#20
0$
1#
#30
0!
1"
1$
#40
0"
1!
1%
0$
0#
#50
1"
0!
1$
#60
0$
1#
#70
1!
1$
