SR_flip_flop/sr.v
module sr_flip_flop(
  input wire clk,
  input wire reset,
  input wire s,
  input wire r,
  output reg q,
  output reg q_bar
);

  always @(posedge clk or posedge reset) begin
    if (reset)
      q <= 1'b0;
    else if (s && ~r)
      q <= 1'b1;
    else if (~s && r)
      q <= 1'b0;
    else if (s && r)
      q <= 1'bz;
  end

  always @(q) begin
    q_bar <= ~q;
  end

endmodule

SR_flip_flop/sr_tb.v
module testbench;

  reg clk, reset, s, r;
  wire q, q_bar;

  sr_flip_flop dut (
    .clk(clk),
    .reset(reset),
    .s(s),
    .r(r),
    .q(q),
    .q_bar(q_bar)
  );

  initial begin
    $dumpfile("sr.vcd");
    $dumpvars(1);
    clk = 0;
    reset = 1;
    s = 0;
    r = 0;

    #5 reset = 0;

    #5 s = 1;
    #10 s = 0;

    #5 r = 1;
    #10 r = 0;

    #5 s = 1;
    #5 r = 1;

    #5 s = 0;
    #5 r = 0;

    #5 s = 1;
    #10 s = 0;

    #5 r = 1;
    #10 r = 0;

    #5 $finish;
  end

  always #1 clk = ~clk;

endmodule

SR_flip_flop/sr.vcd
$date
	Mon Jun  5 10:51:30 2023
$end
$version
	Icarus Verilog
$end
$timescale
	1s
$end
$scope module testbench $end
$var wire 1 ! q_bar $end
$var wire 1 " q $end
$var reg 1 # clk $end
$var reg 1 $ r $end
$var reg 1 % reset $end
$var reg 1 & s $end
$upscope $end
$enddefinitions $end
#0
$dumpvars
0&
1%
0$
0#
0"
1!
$end
#1
1#
#2
0#
#3
1#
#4
0#
#5
1#
0%
#6
0#
#7
1#
#8
0#
#9
1#
#10
0#
1&
#11
0!
1"
1#
#12
0#
#13
1#
#14
0#
#15
1#
#16
0#
#17
1#
#18
0#
#19
1#
#20
0#
0&
#21
1#
#22
0#
#23
1#
#24
0#
#25
1!
0"
1#
1$
#26
0#
#27
1#
#28
0#
#29
1#
#30
0#
#31
1#
#32
0#
#33
1#
#34
0#
#35
1#
0$
#36
0#
#37
1#
#38
0#
#39
1#
#40
0#
1&
#41
0!
1"
1#
#42
0#
#43
1#
#44
0#
#45
x!
z"
1#
1$
#46
0#
#47
1#
#48
0#
#49
1#
#50
0#
0&
#51
1!
0"
1#
#52
0#
#53
1#
#54
0#
#55
1#
0$
#56
0#
#57
1#
#58
0#
#59
1#
#60
0#
1&
#61
0!
1"
1#
#62
0#
#63
1#
#64
0#
#65
1#
#66
0#
#67
1#
#68
0#
#69
1#
#70
0#
0&
#71
1#
#72
0#
#73
1#
#74
0#
#75
1!
0"
1#
1$
#76
0#
#77
1#
#78
0#
#79
1#
#80
0#
#81
1#
#82
0#
#83
1#
#84
0#
#85
1#
0$
