Code Converters/bintoexcess3/bintoex3.v
module bintoex3 (
    input [3:0] binary,
    output reg [3:0] excess3
);

always @(*) begin
    case(binary)
        4'b0000: excess3 = 4'b0011;
        4'b0001: excess3 = 4'b0100;
        4'b0010: excess3 = 4'b0101;
        4'b0011: excess3 = 4'b0110;
        4'b0100: excess3 = 4'b0111;
        4'b0101: excess3 = 4'b1000;
        4'b0110: excess3 = 4'b1001;
        4'b0111: excess3 = 4'b1010;
        4'b1000: excess3 = 4'b1011;
        4'b1001: excess3 = 4'b1100;
        4'b1010: excess3 = 4'b1101;
        4'b1011: excess3 = 4'b1110;
        4'b1100: excess3 = 4'b1111;
        4'b1101: excess3 = 4'b0000;
        4'b1110: excess3 = 4'b0001;
        4'b1111: excess3 = 4'b0010;
        default: excess3 = 4'bxxxx; 
    endcase
end

endmodule

Code Converters/bintoexcess3/tb_bintoex3.v
module tb_bintoex3;
reg [3:0] binary;
wire [3:0] excess3;

bintoex3 uut (.binary(binary), .excess3(excess3));
initial begin
    $dumpfile("bintoex3.vcd");
    $dumpvars(0, tb_bintoex3);
    $monitor($time, " Binary Input: %b, Excess-3 Output: %b", binary, excess3);

    binary = 4'b0000;
    #10 binary = 4'b0001;
    #10 binary = 4'b0010;
    #10 binary = 4'b0011;
    #10 binary = 4'b0100;
    #10 binary = 4'b0101;
    #10 binary = 4'b0110;
    #10 binary = 4'b0111;
    #10 binary = 4'b1000;
    #10 binary = 4'b1001;
    #10 binary = 4'b1010;
    #10 binary = 4'b1011;
    #10 binary = 4'b1100;
    #10 binary = 4'b1101;
    #10 binary = 4'b1110;
    #10 binary = 4'b1111;
    #10 $finish;
end
endmodule

Code Converters/bintoexcess3/bintoex3.vcd
$date
	Fri Mar  1 08:28:37 2024
$end
$version
	Icarus Verilog
$end
$timescale
	1s
$end
$scope module tb_bintoex3 $end
$var wire 4 ! excess3 [3:0] $end
$var reg 4 " binary [3:0] $end
$scope module uut $end
$var wire 4 # binary [3:0] $end
$var reg 4 $ excess3 [3:0] $end
$upscope $end
$upscope $end
$enddefinitions $end
#0
$dumpvars
b11 $
b0 #
b0 "
b11 !
$end
#10
b100 !
b100 $
b1 "
b1 #
#20
b101 !
b101 $
b10 "
b10 #
#30
b110 !
b110 $
b11 "
b11 #
#40
b111 !
b111 $
b100 "
b100 #
#50
b1000 !
b1000 $
b101 "
b101 #
#60
b1001 !
b1001 $
b110 "
b110 #
#70
b1010 !
b1010 $
b111 "
b111 #
#80
b1011 !
b1011 $
b1000 "
b1000 #
#90
b1100 !
b1100 $
b1001 "
b1001 #
#100
b1101 !
b1101 $
b1010 "
b1010 #
#110
b1110 !
b1110 $
b1011 "
b1011 #
#120
b1111 !
b1111 $
b1100 "
b1100 #
#130
b0 !
b0 $
b1101 "
b1101 #
#140
b1 !
b1 $
b1110 "
b1110 #
#150
b10 !
b10 $
b1111 "
b1111 #
