Rippple_carry_adder/ripple_adder.v
module full_adder(a,b,cin,sum,cout);
    input a,b,cin;
	output sum,cout;
    xor G1(w1, a, b);
    xor G2(a, w1, cin);
    and G3(w2, w1, cin);
    and G4(w3, a, b);
    or G5(Co, w2, w3);
endmodule

module ripple_adder(a, b, sum, cout);
  input [3:0] a, b;
  output [3:0] sum;
  output cout;
  wire w1, w2, w3;
  
  full_adder u1(a[0], b[0], 1'b0, sum[0], w1);
  full_adder u2(a[1], b[1], w1, sum[1], w2);
  full_adder u3(a[2], b[2], w2, sum[2], w3);
  full_adder u4(a[3], b[3], w3, sum[3], cout);

endmodule

Full_adder/fa_tb.v


module fa_tb;
    reg a, b, cin;
    wire sum, cout;

    full_adder DUT(a, b, cin, sum, cout);

    initial begin
    	$dumpfile("full_adder.vcd"); 
        $dumpvars(0, fa_tb); 
        $display("Full Adder Testbench");
        $display("--------------------");
        $display("Inputs\t\t|\tOutputs");
        $display("--------------------");

        // Test case 1
        a = 0; b = 0; cin = 0;
        #10;
        $display("%b %b %b\t|\t%b %b", a, b, cin, sum, cout);

        // Test case 2
        a = 0; b = 1; cin = 0;
        #10;
        $display("%b %b %b\t|\t%b %b", a, b, cin, sum, cout);

        // Test case 3
        a = 1; b = 0; cin = 0;
        #10;
        $display("%b %b %b\t|\t%b %b", a, b, cin, sum, cout);

        // Test case 4
        a = 1; b = 1; cin = 0;
        #10;
        $display("%b %b %b\t|\t%b %b", a, b, cin, sum, cout);
	
	// Test case 5
        a = 0; b = 0; cin = 1;
        #10;
        $display("%b %b %b\t|\t%b %b", a, b, cin, sum, cout);

        // Test case 6
        a = 0; b = 1; cin = 1;
        #10;
        $display("%b %b %b\t|\t%b %b", a, b, cin, sum, cout);

        // Test case 7
        a = 1; b = 0; cin = 1;
        #10;
        $display("%b %b %b\t|\t%b %b", a, b, cin, sum, cout);

        // Test case 8
        a = 1; b = 1; cin = 1;
        #10;
        $display("%b %b %b\t|\t%b %b", a, b, cin, sum, cout);

        $finish;
    end
endmodule

Full_adder/full_adder.vcd
$date
	Mon Jun  5 12:58:28 2023
$end
$version
	Icarus Verilog
$end
$timescale
	1s
$end
$scope module fa_tb $end
$var wire 1 ! sum $end
$var wire 1 " cout $end
$var reg 1 # a $end
$var reg 1 $ b $end
$var reg 1 % cin $end
$scope module DUT $end
$var wire 1 # a $end
$var wire 1 $ b $end
$var wire 1 % cin $end
$var wire 1 " cout $end
$var wire 1 ! sum $end
$upscope $end
$upscope $end
$enddefinitions $end
#0
$dumpvars
0%
0$
0#
0"
0!
$end
#10
1!
1$
#20
0$
1#
#30
0!
1"
1$
#40
0"
1!
1%
0$
0#
#50
1"
0!
1$
#60
0$
1#
#70
1!
1$
