Latches/T_latch/t.v
module t_latch(input t, input reset, output reg q);

    always @(posedge t or posedge reset)
    begin
        if (reset)
            q <= 1'b0;
        else if (t)
            q <= ~q;
    end

endmodule

Latches/T_latch/tb_t.v
module tb_t_latch;
    reg t, reset;
    wire q;
    t_latch dut(.t(t),.reset(reset),.q(q));

    initial begin
        $dumpfile("waveform.vcd");
        $dumpvars(0, tb_t_latch);

        $monitor("Time=%0t, t=%b, reset=%b, q=%b", $time, t, reset, q);
        reset = 1'b1;
        #10 reset = 1'b0;
        #5 t = 1'b1; 
        #5 t = 1'b0;
        #5 t = 1'b1;
        #5 t = 1'b0;
        #5 t = 1'b1;
        #5 t = 1'b0;
        #5 $finish;
    end

endmodule

Latches/T_latch/waveform.vcd
$date
	Fri Apr 12 07:46:09 2024
$end
$version
	Icarus Verilog
$end
$timescale
	1s
$end
$scope module tb_t_latch $end
$var wire 1 ! q $end
$var reg 1 " reset $end
$var reg 1 # t $end
$scope module t_latch_inst $end
$var wire 1 " reset $end
$var wire 1 # t $end
$var reg 1 ! q $end
$upscope $end
$upscope $end
$enddefinitions $end
#0
$dumpvars
x#
1"
0!
$end
#10
0"
#15
1!
1#
#20
0#
#25
0!
1#
#30
0#
#35
1!
1#
#40
0#
